zato_apitest-24.10.1-py3.10-nspkg.pth
zato/apitest/__init__.py
zato/apitest/cli.py
zato/apitest/init.py
zato/apitest/run.py
zato/apitest/typing_.py
zato/apitest/util.py
zato/apitest/steps/__init__.py
zato/apitest/steps/common.py
zato/apitest/steps/json.py
zato_apitest-24.10.1.data/scripts/apitest
zato_apitest-24.10.1.dist-info/LICENSE.txt
zato_apitest-24.10.1.dist-info/METADATA
zato_apitest-24.10.1.dist-info/WHEEL
zato_apitest-24.10.1.dist-info/namespace_packages.txt
zato_apitest-24.10.1.dist-info/top_level.txt
zato_apitest-24.10.1.dist-info/RECORD
