Metadata-Version: 2.1
Name: zato-apitest
Version: 24.10.1
Summary: API Testing for Humans. Write API tests in pure English, without any programming needed.
Home-page: https://zato.io
Author: Zato Source s.r.o.
Author-email: info@zato.io
License: SSPL 1.0
Platform: OS Independent
Classifier: Development Status :: 5 - Production/Stable
Classifier: Environment :: Console
Classifier: Environment :: Web Environment
Classifier: Intended Audience :: Developers
Classifier: Intended Audience :: Information Technology
Classifier: Intended Audience :: Other Audience
Classifier: Natural Language :: English
Classifier: Operating System :: OS Independent
Classifier: Programming Language :: Python
Classifier: Programming Language :: Python :: 2
Classifier: Programming Language :: Python :: 3
Classifier: Intended Audience :: Developers
Classifier: Topic :: Communications
Classifier: Topic :: Education :: Testing
Classifier: Topic :: Internet
Classifier: Topic :: Internet :: Proxy Servers
Classifier: Topic :: Internet :: WWW/HTTP
Classifier: Topic :: Security
Classifier: Topic :: Software Development :: Quality Assurance
Classifier: Topic :: Software Development :: Testing
Classifier: Topic :: System :: Networking
Classifier: Topic :: Utilities
License-File: LICENSE.txt
Requires-Dist: argparse>=1.4.0
Requires-Dist: arrow>=1.3.0
Requires-Dist: base32-crockford>=0.3.0
Requires-Dist: behave>=1.2.6
Requires-Dist: click>=8.1.7
Requires-Dist: configobj>=5.0.8
Requires-Dist: datadiff>=2.2.0
Requires-Dist: flake8>=7.0.0
Requires-Dist: jsonpointer>=2.4
Requires-Dist: lxml>=5.1.0
Requires-Dist: parse>=1.20.1
Requires-Dist: parse-type>=0.6.2
Requires-Dist: pep8>=1.7.1
Requires-Dist: pyflakes>=3.2.0
Requires-Dist: python-dateutil>=2.9.0.post0
Requires-Dist: requests>=2.31.0
Requires-Dist: requests-testadapter>=0.3.0
Requires-Dist: twine>=5.0.0
Requires-Dist: typing-extensions>=4.10.0
Requires-Dist: wheel>=0.42.0
Requires-Dist: zato-ext-bunch==1.2
